LICENSE.txt
MANIFEST.in
README.md
setup.cfg
setup.py
capturewrap/__init__.py
capturewrap/builders.py
capturewrap/models.py
capturewrap.egg-info/PKG-INFO
capturewrap.egg-info/SOURCES.txt
capturewrap.egg-info/dependency_links.txt
capturewrap.egg-info/top_level.txt
capturewrap.egg-info/zip-safe
capturewrap/tests/__init__.py
capturewrap/tests/test_builders.py
capturewrap/tests/test_models.py