Metadata-Version: 1.0
Name: capturewrap
Version: 1.1.0
Summary: Wraps callables to capture stdout, stderr, exceptions and the return
Home-page: https://github.com/wtsi-hgi/python-capturewrap
Author: UNKNOWN
Author-email: UNKNOWN
License: MIT
Platform: UNKNOWN
